package com.baidu.mobstat;

import android.content.Context;
import android.text.TextUtils;
import org.json.JSONArray;
import org.json.JSONException;
import org.json.JSONObject;

public class DataCore
{
  private static JSONObject a = new JSONObject();
  private static DataCore b = new DataCore();
  private JSONArray c = new JSONArray();
  private JSONArray d = new JSONArray();
  private JSONArray e = new JSONArray();
  private boolean f = false;
  private volatile int g = 0;
  private StatService.WearListener h;
  
  private void a(Context paramContext)
  {
    clearCache(paramContext);
    CooperService.a().setHeadSqCounted(true);
    ch.a().d();
  }
  
  private void a(Context paramContext, String paramString)
  {
    if ((this.h != null) && (this.h.onSendLogData(paramString)))
    {
      cz.a("log data has been passed to app level");
      return;
    }
    by.a().a(paramContext, paramString);
  }
  
  /* Error */
  private void a(JSONObject paramJSONObject, String paramString1, String paramString2, String paramString3, long paramLong, String paramString4, String paramString5, int paramInt, boolean paramBoolean)
  {
    // Byte code:
    //   0: aload_0
    //   1: getfield 39	com/baidu/mobstat/DataCore:d	Lorg/json/JSONArray;
    //   4: astore 24
    //   6: aload 24
    //   8: monitorenter
    //   9: aload_0
    //   10: getfield 39	com/baidu/mobstat/DataCore:d	Lorg/json/JSONArray;
    //   13: invokevirtual 95	org/json/JSONArray:length	()I
    //   16: istore 15
    //   18: aload 4
    //   20: ifnull +13 -> 33
    //   23: aload 4
    //   25: ldc 97
    //   27: invokevirtual 103	java/lang/String:equals	(Ljava/lang/Object;)Z
    //   30: ifeq +20 -> 50
    //   33: aload_1
    //   34: ldc 105
    //   36: ldc 107
    //   38: invokevirtual 111	org/json/JSONObject:put	(Ljava/lang/String;Ljava/lang/Object;)Lorg/json/JSONObject;
    //   41: pop
    //   42: goto +8 -> 50
    //   45: ldc 113
    //   47: invokestatic 81	com/baidu/mobstat/cz:a	(Ljava/lang/String;)V
    //   50: iload 15
    //   52: istore 11
    //   54: iconst_0
    //   55: istore 12
    //   57: iload 12
    //   59: iload 15
    //   61: if_icmpge +450 -> 511
    //   64: aload_0
    //   65: getfield 39	com/baidu/mobstat/DataCore:d	Lorg/json/JSONArray;
    //   68: iload 12
    //   70: invokevirtual 117	org/json/JSONArray:getJSONObject	(I)Lorg/json/JSONObject;
    //   73: astore 25
    //   75: aload 25
    //   77: ldc 119
    //   79: invokevirtual 123	org/json/JSONObject:getString	(Ljava/lang/String;)Ljava/lang/String;
    //   82: astore 4
    //   84: aload 25
    //   86: ldc 125
    //   88: invokevirtual 123	org/json/JSONObject:getString	(Ljava/lang/String;)Ljava/lang/String;
    //   91: astore 23
    //   93: aload 25
    //   95: ldc 127
    //   97: invokevirtual 131	org/json/JSONObject:getLong	(Ljava/lang/String;)J
    //   100: ldc2_w 132
    //   103: ldiv
    //   104: lstore 17
    //   106: aload 25
    //   108: ldc -122
    //   110: invokevirtual 138	org/json/JSONObject:getInt	(Ljava/lang/String;)I
    //   113: istore 13
    //   115: goto +11 -> 126
    //   118: ldc -116
    //   120: invokestatic 81	com/baidu/mobstat/cz:a	(Ljava/lang/String;)V
    //   123: iconst_0
    //   124: istore 13
    //   126: aload 25
    //   128: ldc -115
    //   130: invokevirtual 144	org/json/JSONObject:optString	(Ljava/lang/String;)Ljava/lang/String;
    //   133: astore 26
    //   135: aload 25
    //   137: ldc -110
    //   139: invokevirtual 144	org/json/JSONObject:optString	(Ljava/lang/String;)Ljava/lang/String;
    //   142: astore 27
    //   144: aload 25
    //   146: ldc -108
    //   148: invokevirtual 151	org/json/JSONObject:optInt	(Ljava/lang/String;)I
    //   151: istore 16
    //   153: iload 11
    //   155: istore 14
    //   157: aload 25
    //   159: ldc -103
    //   161: invokevirtual 156	org/json/JSONObject:optBoolean	(Ljava/lang/String;)Z
    //   164: istore 21
    //   166: lload 17
    //   168: lload 5
    //   170: lcmp
    //   171: ifne +248 -> 419
    //   174: iload 13
    //   176: ifeq +6 -> 182
    //   179: goto +240 -> 419
    //   182: aload 4
    //   184: aload_2
    //   185: invokevirtual 103	java/lang/String:equals	(Ljava/lang/Object;)Z
    //   188: ifeq +219 -> 407
    //   191: aload 23
    //   193: aload_3
    //   194: invokevirtual 103	java/lang/String:equals	(Ljava/lang/Object;)Z
    //   197: ifeq +210 -> 407
    //   200: aload 26
    //   202: aload 7
    //   204: invokevirtual 103	java/lang/String:equals	(Ljava/lang/Object;)Z
    //   207: istore 22
    //   209: iload 22
    //   211: ifeq +196 -> 407
    //   214: aload 27
    //   216: aload 8
    //   218: invokevirtual 103	java/lang/String:equals	(Ljava/lang/Object;)Z
    //   221: istore 22
    //   223: iload 22
    //   225: ifeq +182 -> 407
    //   228: iload 16
    //   230: iload 9
    //   232: if_icmpne +175 -> 407
    //   235: iload 14
    //   237: istore 13
    //   239: iload 21
    //   241: iload 10
    //   243: if_icmpne +255 -> 498
    //   246: aload_1
    //   247: ldc -99
    //   249: invokevirtual 138	org/json/JSONObject:getInt	(Ljava/lang/String;)I
    //   252: istore 13
    //   254: aload 25
    //   256: ldc -99
    //   258: invokevirtual 138	org/json/JSONObject:getInt	(Ljava/lang/String;)I
    //   261: istore 14
    //   263: aload 25
    //   265: ldc 105
    //   267: invokevirtual 144	org/json/JSONObject:optString	(Ljava/lang/String;)Ljava/lang/String;
    //   270: astore 23
    //   272: aload 23
    //   274: ifnull +217 -> 491
    //   277: aload 23
    //   279: astore 4
    //   281: aload 23
    //   283: ldc 97
    //   285: invokevirtual 160	java/lang/String:equalsIgnoreCase	(Ljava/lang/String;)Z
    //   288: ifeq +6 -> 294
    //   291: goto +200 -> 491
    //   294: aload_1
    //   295: ldc 127
    //   297: invokevirtual 131	org/json/JSONObject:getLong	(Ljava/lang/String;)J
    //   300: lstore 17
    //   302: aload 25
    //   304: ldc 127
    //   306: invokevirtual 131	org/json/JSONObject:getLong	(Ljava/lang/String;)J
    //   309: lstore 19
    //   311: new 162	java/lang/StringBuilder
    //   314: dup
    //   315: invokespecial 163	java/lang/StringBuilder:<init>	()V
    //   318: astore 23
    //   320: aload 23
    //   322: aload 4
    //   324: invokevirtual 167	java/lang/StringBuilder:append	(Ljava/lang/String;)Ljava/lang/StringBuilder;
    //   327: pop
    //   328: aload 23
    //   330: lload 17
    //   332: lload 19
    //   334: lsub
    //   335: invokevirtual 170	java/lang/StringBuilder:append	(J)Ljava/lang/StringBuilder;
    //   338: pop
    //   339: aload 23
    //   341: ldc -84
    //   343: invokevirtual 167	java/lang/StringBuilder:append	(Ljava/lang/String;)Ljava/lang/StringBuilder;
    //   346: pop
    //   347: aload 23
    //   349: invokevirtual 176	java/lang/StringBuilder:toString	()Ljava/lang/String;
    //   352: astore 4
    //   354: aload 25
    //   356: ldc -99
    //   358: invokevirtual 180	org/json/JSONObject:remove	(Ljava/lang/String;)Ljava/lang/Object;
    //   361: pop
    //   362: aload 25
    //   364: ldc -99
    //   366: iload 13
    //   368: iload 14
    //   370: iadd
    //   371: invokevirtual 183	org/json/JSONObject:put	(Ljava/lang/String;I)Lorg/json/JSONObject;
    //   374: pop
    //   375: aload 25
    //   377: ldc 105
    //   379: aload 4
    //   381: invokevirtual 111	org/json/JSONObject:put	(Ljava/lang/String;Ljava/lang/Object;)Lorg/json/JSONObject;
    //   384: pop
    //   385: goto +56 -> 441
    //   388: astore 4
    //   390: iload 12
    //   392: istore 13
    //   394: goto +39 -> 433
    //   397: astore 4
    //   399: goto +30 -> 429
    //   402: astore 4
    //   404: goto +20 -> 424
    //   407: iload 14
    //   409: istore 13
    //   411: goto +87 -> 498
    //   414: astore 4
    //   416: goto +8 -> 424
    //   419: goto -12 -> 407
    //   422: astore 4
    //   424: goto +5 -> 429
    //   427: astore 4
    //   429: iload 11
    //   431: istore 13
    //   433: aload 4
    //   435: invokestatic 186	com/baidu/mobstat/cz:a	(Ljava/lang/Throwable;)V
    //   438: goto +60 -> 498
    //   441: iload 12
    //   443: iload 15
    //   445: if_icmpge +7 -> 452
    //   448: aload 24
    //   450: monitorexit
    //   451: return
    //   452: aload_0
    //   453: getfield 39	com/baidu/mobstat/DataCore:d	Lorg/json/JSONArray;
    //   456: iload 15
    //   458: aload_1
    //   459: invokevirtual 189	org/json/JSONArray:put	(ILjava/lang/Object;)Lorg/json/JSONArray;
    //   462: pop
    //   463: goto +8 -> 471
    //   466: astore_1
    //   467: aload_1
    //   468: invokestatic 186	com/baidu/mobstat/cz:a	(Ljava/lang/Throwable;)V
    //   471: aload 24
    //   473: monitorexit
    //   474: return
    //   475: astore_1
    //   476: aload 24
    //   478: monitorexit
    //   479: aload_1
    //   480: athrow
    //   481: astore 4
    //   483: goto -438 -> 45
    //   486: astore 26
    //   488: goto -370 -> 118
    //   491: ldc 107
    //   493: astore 4
    //   495: goto -201 -> 294
    //   498: iload 13
    //   500: istore 11
    //   502: iload 12
    //   504: iconst_1
    //   505: iadd
    //   506: istore 12
    //   508: goto -451 -> 57
    //   511: iload 11
    //   513: istore 12
    //   515: goto -74 -> 441
    // Local variable table:
    //   start	length	slot	name	signature
    //   0	518	0	this	DataCore
    //   0	518	1	paramJSONObject	JSONObject
    //   0	518	2	paramString1	String
    //   0	518	3	paramString2	String
    //   0	518	4	paramString3	String
    //   0	518	5	paramLong	long
    //   0	518	7	paramString4	String
    //   0	518	8	paramString5	String
    //   0	518	9	paramInt	int
    //   0	518	10	paramBoolean	boolean
    //   52	460	11	i	int
    //   55	459	12	j	int
    //   113	386	13	k	int
    //   155	253	14	m	int
    //   16	441	15	n	int
    //   151	82	16	i1	int
    //   104	227	17	l1	long
    //   309	24	19	l2	long
    //   164	80	21	bool1	boolean
    //   207	17	22	bool2	boolean
    //   91	257	23	localObject	Object
    //   4	473	24	localJSONArray	JSONArray
    //   73	303	25	localJSONObject	JSONObject
    //   133	68	26	str1	String
    //   486	1	26	localJSONException	JSONException
    //   142	73	27	str2	String
    // Exception table:
    //   from	to	target	type
    //   354	385	388	org/json/JSONException
    //   246	272	397	org/json/JSONException
    //   281	291	397	org/json/JSONException
    //   294	354	397	org/json/JSONException
    //   214	223	402	org/json/JSONException
    //   182	209	414	org/json/JSONException
    //   157	166	422	org/json/JSONException
    //   64	106	427	org/json/JSONException
    //   118	123	427	org/json/JSONException
    //   126	153	427	org/json/JSONException
    //   452	463	466	org/json/JSONException
    //   9	18	475	finally
    //   23	33	475	finally
    //   33	42	475	finally
    //   45	50	475	finally
    //   64	106	475	finally
    //   106	115	475	finally
    //   118	123	475	finally
    //   126	153	475	finally
    //   157	166	475	finally
    //   182	209	475	finally
    //   214	223	475	finally
    //   246	272	475	finally
    //   281	291	475	finally
    //   294	354	475	finally
    //   354	385	475	finally
    //   433	438	475	finally
    //   448	451	475	finally
    //   452	463	475	finally
    //   467	471	475	finally
    //   471	474	475	finally
    //   476	479	475	finally
    //   23	33	481	org/json/JSONException
    //   33	42	481	org/json/JSONException
    //   106	115	486	org/json/JSONException
  }
  
  private void a(boolean paramBoolean)
  {
    this.f = paramBoolean;
  }
  
  private boolean a()
  {
    return this.f;
  }
  
  private boolean a(String paramString)
  {
    return paramString.getBytes().length + ch.a().b() + this.g > 204800;
  }
  
  private void b(Context paramContext)
  {
    synchronized (this.d)
    {
      this.d = new JSONArray();
      synchronized (this.c)
      {
        this.c = new JSONArray();
        synchronized (this.e)
        {
          this.e = new JSONArray();
          flush(paramContext);
          return;
        }
      }
    }
  }
  
  public static DataCore instance()
  {
    return b;
  }
  
  public void clearCache(Context paramContext)
  {
    a(false);
    synchronized (a)
    {
      a = new JSONObject();
      installHeader(paramContext);
      b(paramContext);
      return;
    }
  }
  
  /* Error */
  public String constructLogWithEmptyBody(Context paramContext, String paramString)
  {
    // Byte code:
    //   0: new 22	org/json/JSONObject
    //   3: dup
    //   4: invokespecial 25	org/json/JSONObject:<init>	()V
    //   7: astore 5
    //   9: new 22	org/json/JSONObject
    //   12: dup
    //   13: invokespecial 25	org/json/JSONObject:<init>	()V
    //   16: astore 6
    //   18: invokestatic 54	com/baidu/mobstat/CooperService:a	()Lcom/baidu/mobstat/CooperService;
    //   21: invokevirtual 217	com/baidu/mobstat/CooperService:getHeadObject	()Lcom/baidu/mobstat/bu;
    //   24: astore 7
    //   26: aload 7
    //   28: getfield 222	com/baidu/mobstat/bu:f	Ljava/lang/String;
    //   31: invokestatic 228	android/text/TextUtils:isEmpty	(Ljava/lang/CharSequence;)Z
    //   34: ifeq +14 -> 48
    //   37: aload 7
    //   39: aload_1
    //   40: aload 6
    //   42: invokevirtual 231	com/baidu/mobstat/bu:a	(Landroid/content/Context;Lorg/json/JSONObject;)V
    //   45: goto +11 -> 56
    //   48: aload 7
    //   50: aload_1
    //   51: aload 6
    //   53: invokevirtual 233	com/baidu/mobstat/bu:b	(Landroid/content/Context;Lorg/json/JSONObject;)V
    //   56: new 34	org/json/JSONArray
    //   59: dup
    //   60: invokespecial 35	org/json/JSONArray:<init>	()V
    //   63: astore_1
    //   64: invokestatic 239	java/lang/System:currentTimeMillis	()J
    //   67: lstore_3
    //   68: aload 6
    //   70: ldc 127
    //   72: lload_3
    //   73: invokevirtual 242	org/json/JSONObject:put	(Ljava/lang/String;J)Lorg/json/JSONObject;
    //   76: pop
    //   77: aload 6
    //   79: ldc -12
    //   81: lload_3
    //   82: invokevirtual 242	org/json/JSONObject:put	(Ljava/lang/String;J)Lorg/json/JSONObject;
    //   85: pop
    //   86: aload 6
    //   88: ldc -10
    //   90: aload_1
    //   91: invokevirtual 111	org/json/JSONObject:put	(Ljava/lang/String;Ljava/lang/Object;)Lorg/json/JSONObject;
    //   94: pop
    //   95: aload 6
    //   97: ldc -8
    //   99: iconst_0
    //   100: invokevirtual 183	org/json/JSONObject:put	(Ljava/lang/String;I)Lorg/json/JSONObject;
    //   103: pop
    //   104: aload 6
    //   106: ldc -6
    //   108: invokestatic 54	com/baidu/mobstat/CooperService:a	()Lcom/baidu/mobstat/CooperService;
    //   111: invokevirtual 253	com/baidu/mobstat/CooperService:getUUID	()Ljava/lang/String;
    //   114: invokevirtual 111	org/json/JSONObject:put	(Ljava/lang/String;Ljava/lang/Object;)Lorg/json/JSONObject;
    //   117: pop
    //   118: aload 6
    //   120: ldc -1
    //   122: aload_2
    //   123: invokevirtual 111	org/json/JSONObject:put	(Ljava/lang/String;Ljava/lang/Object;)Lorg/json/JSONObject;
    //   126: pop
    //   127: aload 5
    //   129: ldc_w 257
    //   132: aload 6
    //   134: invokevirtual 111	org/json/JSONObject:put	(Ljava/lang/String;Ljava/lang/Object;)Lorg/json/JSONObject;
    //   137: pop
    //   138: aload 5
    //   140: ldc_w 259
    //   143: aload_1
    //   144: invokevirtual 111	org/json/JSONObject:put	(Ljava/lang/String;Ljava/lang/Object;)Lorg/json/JSONObject;
    //   147: pop
    //   148: aload 5
    //   150: ldc_w 261
    //   153: aload_1
    //   154: invokevirtual 111	org/json/JSONObject:put	(Ljava/lang/String;Ljava/lang/Object;)Lorg/json/JSONObject;
    //   157: pop
    //   158: aload 5
    //   160: ldc_w 263
    //   163: aload_1
    //   164: invokevirtual 111	org/json/JSONObject:put	(Ljava/lang/String;Ljava/lang/Object;)Lorg/json/JSONObject;
    //   167: pop
    //   168: aload 5
    //   170: invokevirtual 264	org/json/JSONObject:toString	()Ljava/lang/String;
    //   173: areturn
    //   174: astore_1
    //   175: aload_1
    //   176: invokestatic 186	com/baidu/mobstat/cz:a	(Ljava/lang/Throwable;)V
    //   179: aconst_null
    //   180: areturn
    //   181: astore_1
    //   182: aload_1
    //   183: invokestatic 186	com/baidu/mobstat/cz:a	(Ljava/lang/Throwable;)V
    //   186: aconst_null
    //   187: areturn
    //   188: astore_1
    //   189: aload_1
    //   190: invokestatic 186	com/baidu/mobstat/cz:a	(Ljava/lang/Throwable;)V
    //   193: aconst_null
    //   194: areturn
    //   195: astore_1
    //   196: aload_1
    //   197: invokestatic 186	com/baidu/mobstat/cz:a	(Ljava/lang/Throwable;)V
    //   200: aconst_null
    //   201: areturn
    // Local variable table:
    //   start	length	slot	name	signature
    //   0	202	0	this	DataCore
    //   0	202	1	paramContext	Context
    //   0	202	2	paramString	String
    //   67	15	3	l	long
    //   7	162	5	localJSONObject1	JSONObject
    //   16	117	6	localJSONObject2	JSONObject
    //   24	25	7	localbu	bu
    // Exception table:
    //   from	to	target	type
    //   158	168	174	org/json/JSONException
    //   148	158	181	org/json/JSONException
    //   138	148	188	org/json/JSONException
    //   68	138	195	java/lang/Exception
  }
  
  public void flush(Context paramContext)
  {
    label137:
    try
    {
      ??? = new JSONObject();
    }
    finally {}
    try
    {
      synchronized (this.c)
      {
        ((JSONObject)???).put("pr", new JSONArray(this.c.toString()));
        synchronized (this.d)
        {
          ((JSONObject)???).put("ev", new JSONArray(this.d.toString()));
          synchronized (a)
          {
            ((JSONObject)???).put("he", new JSONObject(a.toString()));
          }
        }
      }
    }
    catch (Exception localException)
    {
      break label137;
    }
    cz.a("flushLogWithoutHeader() construct cache error");
    ??? = ((JSONObject)???).toString();
    if (a())
    {
      cz.a("cache.json exceed 204800B,stop flush.");
      return;
    }
    int i = ((String)???).getBytes().length;
    if (i >= 204800)
    {
      a(true);
      return;
    }
    this.g = i;
    ??? = new StringBuilder();
    ((StringBuilder)???).append("flush:cacheFileSize is:");
    ((StringBuilder)???).append(this.g);
    ((StringBuilder)???).append(", capacity is:");
    ((StringBuilder)???).append(204800);
    cz.a(((StringBuilder)???).toString());
    ??? = dc.q(paramContext);
    StringBuilder localStringBuilder = new StringBuilder();
    localStringBuilder.append((String)???);
    localStringBuilder.append("__local_stat_cache.json");
    cs.a(paramContext, localStringBuilder.toString(), (String)???, false);
    synchronized (this.e)
    {
      ??? = this.e.toString();
      localStringBuilder = new StringBuilder();
      localStringBuilder.append("flush wifi data: ");
      localStringBuilder.append((String)???);
      cz.a(localStringBuilder.toString());
      cs.a(paramContext, "__local_ap_info_cache.json", (String)???, false);
      return;
    }
  }
  
  public int getCacheFileSzie()
  {
    return this.g;
  }
  
  public void installHeader(Context paramContext)
  {
    synchronized (a)
    {
      CooperService.a().getHeadObject().a(paramContext, a);
      return;
    }
  }
  
  public boolean isPartEmpty()
  {
    for (;;)
    {
      synchronized (this.c)
      {
        if (this.c.length() == 0)
        {
          bool = true;
          return bool;
        }
      }
      boolean bool = false;
    }
  }
  
  public void loadLastSession(Context paramContext)
  {
    if (paramContext == null) {
      return;
    }
    String str = dc.q(paramContext);
    Object localObject = new StringBuilder();
    ((StringBuilder)localObject).append(str);
    ((StringBuilder)localObject).append("__local_last_session.json");
    str = ((StringBuilder)localObject).toString();
    if (!cs.c(paramContext, str)) {
      return;
    }
    localObject = cs.a(paramContext, str);
    if (TextUtils.isEmpty((CharSequence)localObject))
    {
      cz.a("loadLastSession(): last_session.json file not found.");
      return;
    }
    cs.a(paramContext, str, new JSONObject().toString(), false);
    putSession((String)localObject);
    flush(paramContext);
  }
  
  /* Error */
  public void loadStatData(Context arg1)
  {
    // Byte code:
    //   0: aload_1
    //   1: ifnonnull +4 -> 5
    //   4: return
    //   5: aload_1
    //   6: invokestatic 287	com/baidu/mobstat/dc:q	(Landroid/content/Context;)Ljava/lang/String;
    //   9: astore 7
    //   11: new 162	java/lang/StringBuilder
    //   14: dup
    //   15: invokespecial 163	java/lang/StringBuilder:<init>	()V
    //   18: astore 8
    //   20: aload 8
    //   22: aload 7
    //   24: invokevirtual 167	java/lang/StringBuilder:append	(Ljava/lang/String;)Ljava/lang/StringBuilder;
    //   27: pop
    //   28: aload 8
    //   30: ldc_w 289
    //   33: invokevirtual 167	java/lang/StringBuilder:append	(Ljava/lang/String;)Ljava/lang/StringBuilder;
    //   36: pop
    //   37: aload 8
    //   39: invokevirtual 176	java/lang/StringBuilder:toString	()Ljava/lang/String;
    //   42: astore 7
    //   44: aload_1
    //   45: aload 7
    //   47: invokestatic 306	com/baidu/mobstat/cs:c	(Landroid/content/Context;Ljava/lang/String;)Z
    //   50: ifne +4 -> 54
    //   53: return
    //   54: aload_1
    //   55: aload 7
    //   57: invokestatic 308	com/baidu/mobstat/cs:a	(Landroid/content/Context;Ljava/lang/String;)Ljava/lang/String;
    //   60: astore 8
    //   62: aload 8
    //   64: ldc 97
    //   66: invokevirtual 103	java/lang/String:equals	(Ljava/lang/Object;)Z
    //   69: ifeq +10 -> 79
    //   72: ldc_w 316
    //   75: invokestatic 81	com/baidu/mobstat/cz:a	(Ljava/lang/String;)V
    //   78: return
    //   79: ldc_w 318
    //   82: invokestatic 81	com/baidu/mobstat/cz:a	(Ljava/lang/String;)V
    //   85: aload_0
    //   86: aload 8
    //   88: invokevirtual 194	java/lang/String:getBytes	()[B
    //   91: arraylength
    //   92: putfield 45	com/baidu/mobstat/DataCore:g	I
    //   95: new 162	java/lang/StringBuilder
    //   98: dup
    //   99: invokespecial 163	java/lang/StringBuilder:<init>	()V
    //   102: astore 7
    //   104: aload 7
    //   106: ldc_w 320
    //   109: invokevirtual 167	java/lang/StringBuilder:append	(Ljava/lang/String;)Ljava/lang/StringBuilder;
    //   112: pop
    //   113: aload 7
    //   115: aload_0
    //   116: getfield 45	com/baidu/mobstat/DataCore:g	I
    //   119: invokevirtual 279	java/lang/StringBuilder:append	(I)Ljava/lang/StringBuilder;
    //   122: pop
    //   123: aload 7
    //   125: invokevirtual 176	java/lang/StringBuilder:toString	()Ljava/lang/String;
    //   128: invokestatic 81	com/baidu/mobstat/cz:a	(Ljava/lang/String;)V
    //   131: new 22	org/json/JSONObject
    //   134: dup
    //   135: aload 8
    //   137: invokespecial 268	org/json/JSONObject:<init>	(Ljava/lang/String;)V
    //   140: astore 7
    //   142: new 162	java/lang/StringBuilder
    //   145: dup
    //   146: invokespecial 163	java/lang/StringBuilder:<init>	()V
    //   149: astore 9
    //   151: aload 9
    //   153: ldc_w 322
    //   156: invokevirtual 167	java/lang/StringBuilder:append	(Ljava/lang/String;)Ljava/lang/StringBuilder;
    //   159: pop
    //   160: aload 9
    //   162: aload 8
    //   164: invokevirtual 167	java/lang/StringBuilder:append	(Ljava/lang/String;)Ljava/lang/StringBuilder;
    //   167: pop
    //   168: aload 9
    //   170: invokevirtual 176	java/lang/StringBuilder:toString	()Ljava/lang/String;
    //   173: invokestatic 81	com/baidu/mobstat/cz:a	(Ljava/lang/String;)V
    //   176: invokestatic 239	java/lang/System:currentTimeMillis	()J
    //   179: lstore 4
    //   181: aload 7
    //   183: ldc_w 259
    //   186: invokevirtual 326	org/json/JSONObject:getJSONArray	(Ljava/lang/String;)Lorg/json/JSONArray;
    //   189: astore 8
    //   191: iconst_0
    //   192: istore_3
    //   193: iconst_0
    //   194: istore_2
    //   195: iload_2
    //   196: aload 8
    //   198: invokevirtual 95	org/json/JSONArray:length	()I
    //   201: if_icmpge +40 -> 241
    //   204: aload 8
    //   206: iload_2
    //   207: invokevirtual 117	org/json/JSONArray:getJSONObject	(I)Lorg/json/JSONObject;
    //   210: astore 9
    //   212: lload 4
    //   214: aload 9
    //   216: ldc 105
    //   218: invokevirtual 131	org/json/JSONObject:getLong	(Ljava/lang/String;)J
    //   221: lsub
    //   222: ldc2_w 327
    //   225: lcmp
    //   226: ifle +6 -> 232
    //   229: goto +155 -> 384
    //   232: aload_0
    //   233: aload 9
    //   235: invokevirtual 331	com/baidu/mobstat/DataCore:putSession	(Lorg/json/JSONObject;)V
    //   238: goto +146 -> 384
    //   241: aload 7
    //   243: ldc_w 261
    //   246: invokevirtual 326	org/json/JSONObject:getJSONArray	(Ljava/lang/String;)Lorg/json/JSONArray;
    //   249: astore 8
    //   251: iload_3
    //   252: istore_2
    //   253: iload_2
    //   254: aload 8
    //   256: invokevirtual 95	org/json/JSONArray:length	()I
    //   259: if_icmpge +42 -> 301
    //   262: aload 8
    //   264: iload_2
    //   265: invokevirtual 117	org/json/JSONArray:getJSONObject	(I)Lorg/json/JSONObject;
    //   268: astore 9
    //   270: lload 4
    //   272: aload 9
    //   274: ldc 127
    //   276: invokevirtual 131	org/json/JSONObject:getLong	(Ljava/lang/String;)J
    //   279: lsub
    //   280: ldc2_w 327
    //   283: lcmp
    //   284: ifle +6 -> 290
    //   287: goto +104 -> 391
    //   290: aload_0
    //   291: aload_1
    //   292: aload 9
    //   294: iconst_1
    //   295: invokevirtual 335	com/baidu/mobstat/DataCore:putEvent	(Landroid/content/Context;Lorg/json/JSONObject;Z)V
    //   298: goto +93 -> 391
    //   301: aload_0
    //   302: invokevirtual 337	com/baidu/mobstat/DataCore:isPartEmpty	()Z
    //   305: istore 6
    //   307: iload 6
    //   309: ifne +74 -> 383
    //   312: aload 7
    //   314: ldc_w 257
    //   317: invokevirtual 340	org/json/JSONObject:getJSONObject	(Ljava/lang/String;)Lorg/json/JSONObject;
    //   320: astore 7
    //   322: getstatic 27	com/baidu/mobstat/DataCore:a	Lorg/json/JSONObject;
    //   325: astore_1
    //   326: aload_1
    //   327: monitorenter
    //   328: aload 7
    //   330: putstatic 27	com/baidu/mobstat/DataCore:a	Lorg/json/JSONObject;
    //   333: aload_1
    //   334: monitorexit
    //   335: return
    //   336: astore 7
    //   338: aload_1
    //   339: monitorexit
    //   340: aload 7
    //   342: athrow
    //   343: astore_1
    //   344: aload_1
    //   345: invokestatic 186	com/baidu/mobstat/cz:a	(Ljava/lang/Throwable;)V
    //   348: return
    //   349: astore_1
    //   350: new 162	java/lang/StringBuilder
    //   353: dup
    //   354: invokespecial 163	java/lang/StringBuilder:<init>	()V
    //   357: astore 7
    //   359: aload 7
    //   361: ldc_w 342
    //   364: invokevirtual 167	java/lang/StringBuilder:append	(Ljava/lang/String;)Ljava/lang/StringBuilder;
    //   367: pop
    //   368: aload 7
    //   370: aload_1
    //   371: invokevirtual 345	java/lang/StringBuilder:append	(Ljava/lang/Object;)Ljava/lang/StringBuilder;
    //   374: pop
    //   375: aload 7
    //   377: invokevirtual 176	java/lang/StringBuilder:toString	()Ljava/lang/String;
    //   380: invokestatic 81	com/baidu/mobstat/cz:a	(Ljava/lang/String;)V
    //   383: return
    //   384: iload_2
    //   385: iconst_1
    //   386: iadd
    //   387: istore_2
    //   388: goto -193 -> 195
    //   391: iload_2
    //   392: iconst_1
    //   393: iadd
    //   394: istore_2
    //   395: goto -142 -> 253
    // Local variable table:
    //   start	length	slot	name	signature
    //   0	398	0	this	DataCore
    //   194	201	2	i	int
    //   192	60	3	j	int
    //   179	92	4	l	long
    //   305	3	6	bool	boolean
    //   9	320	7	localObject1	Object
    //   336	5	7	localObject2	Object
    //   357	19	7	localStringBuilder	StringBuilder
    //   18	245	8	localObject3	Object
    //   149	144	9	localObject4	Object
    // Exception table:
    //   from	to	target	type
    //   328	335	336	finally
    //   338	340	336	finally
    //   312	328	343	org/json/JSONException
    //   340	343	343	org/json/JSONException
    //   85	191	349	org/json/JSONException
    //   195	229	349	org/json/JSONException
    //   232	238	349	org/json/JSONException
    //   241	251	349	org/json/JSONException
    //   253	287	349	org/json/JSONException
    //   290	298	349	org/json/JSONException
    //   301	307	349	org/json/JSONException
    //   344	348	349	org/json/JSONException
  }
  
  public void loadWifiData(Context arg1)
  {
    if (??? == null) {
      return;
    }
    if (!cs.c(???, "__local_ap_info_cache.json")) {
      return;
    }
    Object localObject1 = cs.a(???, "__local_ap_info_cache.json");
    try
    {
      JSONArray localJSONArray = new JSONArray((String)localObject1);
      int j = localJSONArray.length();
      localObject1 = localJSONArray;
      if (j >= 10)
      {
        localObject1 = new JSONArray();
        int i = j - 10;
        while (i < j)
        {
          ((JSONArray)localObject1).put(localJSONArray.get(i));
          i += 1;
        }
      }
      for (;;)
      {
        ??? = dc.g(1, ???);
        if (!TextUtils.isEmpty(???)) {
          ((JSONArray)localObject1).put(???);
        }
        synchronized (this.e)
        {
          this.e = ((JSONArray)localObject1);
          localObject1 = new StringBuilder();
          ((StringBuilder)localObject1).append("wifiPart: ");
          ((StringBuilder)localObject1).append(this.e.toString());
          cz.a(((StringBuilder)localObject1).toString());
          return;
        }
      }
    }
    catch (JSONException ???)
    {
      cz.b(???);
      return;
    }
  }
  
  public void putEvent(Context paramContext, String paramString1, String paramString2, int paramInt1, long paramLong1, long paramLong2, String paramString3, String paramString4, int paramInt2, boolean paramBoolean, ExtraInfo paramExtraInfo)
  {
    throw new Runtime("d2j fail translate: java.lang.RuntimeException: can not merge I and Z\r\n\tat com.googlecode.dex2jar.ir.TypeClass.merge(TypeClass.java:100)\r\n\tat com.googlecode.dex2jar.ir.ts.TypeTransformer$TypeRef.updateTypeClass(TypeTransformer.java:174)\r\n\tat com.googlecode.dex2jar.ir.ts.TypeTransformer$TypeAnalyze.copyTypes(TypeTransformer.java:311)\r\n\tat com.googlecode.dex2jar.ir.ts.TypeTransformer$TypeAnalyze.fixTypes(TypeTransformer.java:226)\r\n\tat com.googlecode.dex2jar.ir.ts.TypeTransformer$TypeAnalyze.analyze(TypeTransformer.java:207)\r\n\tat com.googlecode.dex2jar.ir.ts.TypeTransformer.transform(TypeTransformer.java:44)\r\n\tat com.googlecode.d2j.dex.Dex2jar$2.optimize(Dex2jar.java:162)\r\n\tat com.googlecode.d2j.dex.Dex2Asm.convertCode(Dex2Asm.java:414)\r\n\tat com.googlecode.d2j.dex.ExDex2Asm.convertCode(ExDex2Asm.java:42)\r\n\tat com.googlecode.d2j.dex.Dex2jar$2.convertCode(Dex2jar.java:128)\r\n\tat com.googlecode.d2j.dex.Dex2Asm.convertMethod(Dex2Asm.java:509)\r\n\tat com.googlecode.d2j.dex.Dex2Asm.convertClass(Dex2Asm.java:406)\r\n\tat com.googlecode.d2j.dex.Dex2Asm.convertDex(Dex2Asm.java:422)\r\n\tat com.googlecode.d2j.dex.Dex2jar.doTranslate(Dex2jar.java:172)\r\n\tat com.googlecode.d2j.dex.Dex2jar.to(Dex2jar.java:272)\r\n\tat com.googlecode.dex2jar.tools.Dex2jarCmd.doCommandLine(Dex2jarCmd.java:108)\r\n\tat com.googlecode.dex2jar.tools.BaseCmd.doMain(BaseCmd.java:288)\r\n\tat com.googlecode.dex2jar.tools.Dex2jarCmd.main(Dex2jarCmd.java:32)\r\n");
  }
  
  public void putEvent(Context arg1, JSONObject paramJSONObject, boolean paramBoolean)
  {
    if (paramJSONObject == null) {
      return;
    }
    if (a(paramJSONObject.toString()))
    {
      cz.b("data to put exceed limit, will not put");
      return;
    }
    for (;;)
    {
      try
      {
        ??? = paramJSONObject.getString("i");
        str1 = paramJSONObject.getString("l");
        l = paramJSONObject.getLong("t") / 3600000L;
        str2 = paramJSONObject.optString("s");
        str3 = paramJSONObject.optString("h");
        str4 = paramJSONObject.optString("p");
        m = paramJSONObject.optInt("v");
        paramBoolean = paramJSONObject.optBoolean("at");
        str5 = paramJSONObject.optString("ext");
        k = 0;
      }
      catch (JSONException ???)
      {
        String str1;
        long l;
        String str2;
        String str3;
        String str4;
        int m;
        String str5;
        int k;
        int i;
        int j;
        cz.a(???);
        return;
      }
      try
      {
        i = paramJSONObject.getInt("d");
      }
      catch (JSONException localJSONException) {}
    }
    cz.a("old version data, No duration Tag");
    i = 0;
    j = k;
    if (!TextUtils.isEmpty(str5))
    {
      j = k;
      if (!new JSONObject().toString().equals(str5)) {
        j = 1;
      }
    }
    if ((i == 0) && (j == 0))
    {
      a(paramJSONObject, ???, str1, str2, l, str3, str4, m, paramBoolean);
      return;
    }
    synchronized (this.d)
    {
      i = this.d.length();
      try
      {
        paramJSONObject.put("s", "0");
        this.d.put(i, paramJSONObject);
      }
      catch (JSONException paramJSONObject)
      {
        cz.a(paramJSONObject);
      }
      return;
    }
  }
  
  public void putSession(String paramString)
  {
    if (!TextUtils.isEmpty(paramString))
    {
      if (paramString.equals(new JSONObject().toString())) {
        return;
      }
      try
      {
        paramString = new JSONObject(paramString);
        putSession(paramString);
        StringBuilder localStringBuilder = new StringBuilder();
        localStringBuilder.append("Load last session:");
        localStringBuilder.append(paramString);
        cz.a(localStringBuilder.toString());
        return;
      }
      catch (JSONException paramString)
      {
        cz.a(paramString);
      }
    }
  }
  
  public void putSession(JSONObject paramJSONObject)
  {
    if (paramJSONObject == null) {
      return;
    }
    if (a(paramJSONObject.toString()))
    {
      cz.b("data to put exceed limit, will not put");
      return;
    }
    synchronized (this.c)
    {
      int i = this.c.length();
      try
      {
        this.c.put(i, paramJSONObject);
      }
      catch (JSONException paramJSONObject)
      {
        cz.a(paramJSONObject);
      }
      return;
    }
  }
  
  /* Error */
  public void saveLogDataToSend(Context paramContext)
  {
    // Byte code:
    //   0: ldc_w 385
    //   3: invokestatic 81	com/baidu/mobstat/cz:a	(Ljava/lang/String;)V
    //   6: invokestatic 54	com/baidu/mobstat/CooperService:a	()Lcom/baidu/mobstat/CooperService;
    //   9: invokevirtual 217	com/baidu/mobstat/CooperService:getHeadObject	()Lcom/baidu/mobstat/bu;
    //   12: astore 5
    //   14: aload 5
    //   16: ifnull +105 -> 121
    //   19: aload 5
    //   21: getfield 222	com/baidu/mobstat/bu:f	Ljava/lang/String;
    //   24: invokestatic 228	android/text/TextUtils:isEmpty	(Ljava/lang/CharSequence;)Z
    //   27: ifeq +94 -> 121
    //   30: getstatic 27	com/baidu/mobstat/DataCore:a	Lorg/json/JSONObject;
    //   33: astore 4
    //   35: aload 4
    //   37: monitorenter
    //   38: aload 5
    //   40: aload_1
    //   41: getstatic 27	com/baidu/mobstat/DataCore:a	Lorg/json/JSONObject;
    //   44: invokevirtual 231	com/baidu/mobstat/bu:a	(Landroid/content/Context;Lorg/json/JSONObject;)V
    //   47: new 162	java/lang/StringBuilder
    //   50: dup
    //   51: invokespecial 163	java/lang/StringBuilder:<init>	()V
    //   54: astore 6
    //   56: aload 6
    //   58: ldc_w 387
    //   61: invokevirtual 167	java/lang/StringBuilder:append	(Ljava/lang/String;)Ljava/lang/StringBuilder;
    //   64: pop
    //   65: aload 6
    //   67: getstatic 27	com/baidu/mobstat/DataCore:a	Lorg/json/JSONObject;
    //   70: invokevirtual 345	java/lang/StringBuilder:append	(Ljava/lang/Object;)Ljava/lang/StringBuilder;
    //   73: pop
    //   74: aload 6
    //   76: getstatic 27	com/baidu/mobstat/DataCore:a	Lorg/json/JSONObject;
    //   79: invokevirtual 388	org/json/JSONObject:length	()I
    //   82: invokevirtual 279	java/lang/StringBuilder:append	(I)Ljava/lang/StringBuilder;
    //   85: pop
    //   86: aload 6
    //   88: invokevirtual 176	java/lang/StringBuilder:toString	()Ljava/lang/String;
    //   91: invokestatic 81	com/baidu/mobstat/cz:a	(Ljava/lang/String;)V
    //   94: aload 4
    //   96: monitorexit
    //   97: aload 5
    //   99: getfield 222	com/baidu/mobstat/bu:f	Ljava/lang/String;
    //   102: invokestatic 228	android/text/TextUtils:isEmpty	(Ljava/lang/CharSequence;)Z
    //   105: ifeq +16 -> 121
    //   108: ldc_w 390
    //   111: invokestatic 392	com/baidu/mobstat/cz:c	(Ljava/lang/String;)V
    //   114: return
    //   115: astore_1
    //   116: aload 4
    //   118: monitorexit
    //   119: aload_1
    //   120: athrow
    //   121: new 22	org/json/JSONObject
    //   124: dup
    //   125: invokespecial 25	org/json/JSONObject:<init>	()V
    //   128: astore 7
    //   130: getstatic 27	com/baidu/mobstat/DataCore:a	Lorg/json/JSONObject;
    //   133: astore 4
    //   135: aload 4
    //   137: monitorenter
    //   138: invokestatic 239	java/lang/System:currentTimeMillis	()J
    //   141: lstore_2
    //   142: getstatic 27	com/baidu/mobstat/DataCore:a	Lorg/json/JSONObject;
    //   145: ldc 127
    //   147: lload_2
    //   148: invokevirtual 242	org/json/JSONObject:put	(Ljava/lang/String;J)Lorg/json/JSONObject;
    //   151: pop
    //   152: getstatic 27	com/baidu/mobstat/DataCore:a	Lorg/json/JSONObject;
    //   155: ldc -12
    //   157: invokestatic 63	com/baidu/mobstat/ch:a	()Lcom/baidu/mobstat/ch;
    //   160: invokevirtual 394	com/baidu/mobstat/ch:g	()J
    //   163: invokevirtual 242	org/json/JSONObject:put	(Ljava/lang/String;J)Lorg/json/JSONObject;
    //   166: pop
    //   167: aload_0
    //   168: getfield 41	com/baidu/mobstat/DataCore:e	Lorg/json/JSONArray;
    //   171: astore 5
    //   173: aload 5
    //   175: monitorenter
    //   176: getstatic 27	com/baidu/mobstat/DataCore:a	Lorg/json/JSONObject;
    //   179: ldc -10
    //   181: aload_0
    //   182: getfield 41	com/baidu/mobstat/DataCore:e	Lorg/json/JSONArray;
    //   185: invokevirtual 111	org/json/JSONObject:put	(Ljava/lang/String;Ljava/lang/Object;)Lorg/json/JSONObject;
    //   188: pop
    //   189: aload 5
    //   191: monitorexit
    //   192: getstatic 27	com/baidu/mobstat/DataCore:a	Lorg/json/JSONObject;
    //   195: ldc -6
    //   197: invokestatic 54	com/baidu/mobstat/CooperService:a	()Lcom/baidu/mobstat/CooperService;
    //   200: invokevirtual 253	com/baidu/mobstat/CooperService:getUUID	()Ljava/lang/String;
    //   203: invokevirtual 111	org/json/JSONObject:put	(Ljava/lang/String;Ljava/lang/Object;)Lorg/json/JSONObject;
    //   206: pop
    //   207: aload 7
    //   209: ldc_w 257
    //   212: getstatic 27	com/baidu/mobstat/DataCore:a	Lorg/json/JSONObject;
    //   215: invokevirtual 111	org/json/JSONObject:put	(Ljava/lang/String;Ljava/lang/Object;)Lorg/json/JSONObject;
    //   218: pop
    //   219: aload_0
    //   220: getfield 37	com/baidu/mobstat/DataCore:c	Lorg/json/JSONArray;
    //   223: astore 5
    //   225: aload 5
    //   227: monitorenter
    //   228: aload 7
    //   230: ldc_w 259
    //   233: aload_0
    //   234: getfield 37	com/baidu/mobstat/DataCore:c	Lorg/json/JSONArray;
    //   237: invokevirtual 111	org/json/JSONObject:put	(Ljava/lang/String;Ljava/lang/Object;)Lorg/json/JSONObject;
    //   240: pop
    //   241: aload_0
    //   242: getfield 39	com/baidu/mobstat/DataCore:d	Lorg/json/JSONArray;
    //   245: astore 6
    //   247: aload 6
    //   249: monitorenter
    //   250: aload 7
    //   252: ldc_w 261
    //   255: aload_0
    //   256: getfield 39	com/baidu/mobstat/DataCore:d	Lorg/json/JSONArray;
    //   259: invokevirtual 111	org/json/JSONObject:put	(Ljava/lang/String;Ljava/lang/Object;)Lorg/json/JSONObject;
    //   262: pop
    //   263: aload 7
    //   265: ldc_w 263
    //   268: new 34	org/json/JSONArray
    //   271: dup
    //   272: invokespecial 35	org/json/JSONArray:<init>	()V
    //   275: invokevirtual 111	org/json/JSONObject:put	(Ljava/lang/String;Ljava/lang/Object;)Lorg/json/JSONObject;
    //   278: pop
    //   279: aload 7
    //   281: invokevirtual 264	org/json/JSONObject:toString	()Ljava/lang/String;
    //   284: astore 7
    //   286: new 162	java/lang/StringBuilder
    //   289: dup
    //   290: invokespecial 163	java/lang/StringBuilder:<init>	()V
    //   293: astore 8
    //   295: aload 8
    //   297: ldc_w 396
    //   300: invokevirtual 167	java/lang/StringBuilder:append	(Ljava/lang/String;)Ljava/lang/StringBuilder;
    //   303: pop
    //   304: aload 8
    //   306: aload 7
    //   308: invokevirtual 167	java/lang/StringBuilder:append	(Ljava/lang/String;)Ljava/lang/StringBuilder;
    //   311: pop
    //   312: aload 8
    //   314: invokevirtual 176	java/lang/StringBuilder:toString	()Ljava/lang/String;
    //   317: invokestatic 81	com/baidu/mobstat/cz:a	(Ljava/lang/String;)V
    //   320: aload_0
    //   321: aload_1
    //   322: aload 7
    //   324: invokespecial 397	com/baidu/mobstat/DataCore:a	(Landroid/content/Context;Ljava/lang/String;)V
    //   327: aload_0
    //   328: aload_1
    //   329: invokespecial 399	com/baidu/mobstat/DataCore:a	(Landroid/content/Context;)V
    //   332: aload 6
    //   334: monitorexit
    //   335: aload 5
    //   337: monitorexit
    //   338: aload 4
    //   340: monitorexit
    //   341: return
    //   342: astore_1
    //   343: aload_1
    //   344: invokestatic 186	com/baidu/mobstat/cz:a	(Ljava/lang/Throwable;)V
    //   347: aload 6
    //   349: monitorexit
    //   350: aload 5
    //   352: monitorexit
    //   353: aload 4
    //   355: monitorexit
    //   356: return
    //   357: astore_1
    //   358: goto +18 -> 376
    //   361: astore_1
    //   362: aload_1
    //   363: invokestatic 186	com/baidu/mobstat/cz:a	(Ljava/lang/Throwable;)V
    //   366: aload 6
    //   368: monitorexit
    //   369: aload 5
    //   371: monitorexit
    //   372: aload 4
    //   374: monitorexit
    //   375: return
    //   376: aload 6
    //   378: monitorexit
    //   379: aload_1
    //   380: athrow
    //   381: astore_1
    //   382: aload_1
    //   383: invokestatic 186	com/baidu/mobstat/cz:a	(Ljava/lang/Throwable;)V
    //   386: aload 5
    //   388: monitorexit
    //   389: aload 4
    //   391: monitorexit
    //   392: return
    //   393: aload 5
    //   395: monitorexit
    //   396: aload_1
    //   397: athrow
    //   398: astore_1
    //   399: aload 5
    //   401: monitorexit
    //   402: aload_1
    //   403: athrow
    //   404: astore_1
    //   405: aload_1
    //   406: invokestatic 186	com/baidu/mobstat/cz:a	(Ljava/lang/Throwable;)V
    //   409: aload 4
    //   411: monitorexit
    //   412: return
    //   413: astore_1
    //   414: aload 4
    //   416: monitorexit
    //   417: aload_1
    //   418: athrow
    //   419: astore_1
    //   420: goto -27 -> 393
    // Local variable table:
    //   start	length	slot	name	signature
    //   0	423	0	this	DataCore
    //   0	423	1	paramContext	Context
    //   141	7	2	l	long
    //   33	382	4	localJSONObject	JSONObject
    //   128	195	7	localObject3	Object
    //   293	20	8	localStringBuilder	StringBuilder
    // Exception table:
    //   from	to	target	type
    //   38	97	115	finally
    //   116	119	115	finally
    //   263	279	342	org/json/JSONException
    //   250	263	357	finally
    //   263	279	357	finally
    //   279	335	357	finally
    //   343	350	357	finally
    //   362	369	357	finally
    //   376	379	357	finally
    //   250	263	361	org/json/JSONException
    //   228	241	381	org/json/JSONException
    //   176	192	398	finally
    //   399	402	398	finally
    //   142	176	404	java/lang/Exception
    //   192	219	404	java/lang/Exception
    //   402	404	404	java/lang/Exception
    //   138	142	413	finally
    //   142	176	413	finally
    //   192	219	413	finally
    //   219	228	413	finally
    //   338	341	413	finally
    //   353	356	413	finally
    //   372	375	413	finally
    //   389	392	413	finally
    //   396	398	413	finally
    //   402	404	413	finally
    //   405	412	413	finally
    //   414	417	413	finally
    //   228	241	419	finally
    //   241	250	419	finally
    //   335	338	419	finally
    //   350	353	419	finally
    //   369	372	419	finally
    //   379	381	419	finally
    //   382	389	419	finally
    //   393	396	419	finally
  }
}


/* Location:              C:\Users\12724\Desktop\classes-dex2jar.jar!\com\baidu\mobstat\DataCore.class
 * Java compiler version: 6 (50.0)
 * JD-Core Version:       0.7.1
 */